{"name": "IGEM Teams", "children": [{"name": "Alma", "children": [{"name": "Brainstorming", "children": [{"name": 2380, "value": 1}, {"name": 2389, "value": 3}]}, {"name": "Collecting data / running assays", "children": [{"name": 2380, "value": 1}]}, {"name": "Education event", "children": [{"name": 2380, "value": 1}]}, {"name": "Project administration", "children": [{"name": 2389, "value": 1}]}, {"name": "Software development", "children": [{"name": 2380, "value": 1}]}, {"name": "Team meetings", "children": [{"name": 2389, "value": 3}]}, {"name": "Writing / preparing presentations", "children": [{"name": 2389, "value": 1}]}]}, {"name": "Ciencias_UNAM", "children": [{"name": "Writing / preparing presentations", "children": [{"name": 2387, "value": 1}]}]}, {"name": "Estonia_TUIT", "children": [{"name": "Analysing results", "children": [{"name": 465, "value": 2}]}, {"name": "Brainstorming", "children": [{"name": 465, "value": 3}, {"name": 466, "value": 1}, {"name": 2400, "value": 1}]}, {"name": "Collecting data / running assays", "children": [{"name": 465, "value": 1}]}, {"name": "Developing protocols", "children": [{"name": 465, "value": 2}]}, {"name": "Interpreting results", "children": [{"name": 465, "value": 2}]}, {"name": "Lab maintenance", "children": [{"name": 465, "value": 2}]}, {"name": "Meetups", "children": [{"name": 465, "value": 1}]}, {"name": "Planning tasks", "children": [{"name": 465, "value": 3}, {"name": 466, "value": 1}, {"name": 2392, "value": 1}, {"name": 2400, "value": 1}]}, {"name": "Preparing samples", "children": [{"name": 465, "value": 2}]}, {"name": "Reading papers or other material", "children": [{"name": 465, "value": 1}]}, {"name": "Team meetings", "children": [{"name": 465, "value": 3}, {"name": 2392, "value": 1}]}, {"name": "Writing / preparing presentations", "children": [{"name": 2400, "value": 1}]}]}, {"name": "GO_Paris-Saclay", "children": [{"name": "Meetups", "children": [{"name": 573, "value": 1}, {"name": 2388, "value": 1}]}, {"name": "No iGEM work", "children": [{"name": 2388, "value": 1}]}, {"name": "Planning tasks", "children": [{"name": 573, "value": 4}]}, {"name": "Project administration", "children": [{"name": 575, "value": 2}, {"name": 2388, "value": 1}]}, {"name": "Reading papers or other material", "children": [{"name": 2388, "value": 1}]}, {"name": "Safety management", "children": [{"name": 2388, "value": 1}]}, {"name": "Software development", "children": [{"name": 2388, "value": 1}]}, {"name": "Team meetings", "children": [{"name": 573, "value": 2}, {"name": 575, "value": 2}, {"name": 579, "value": 1}, {"name": 2388, "value": 1}]}, {"name": "Writing / preparing presentations", "children": [{"name": 2388, "value": 1}]}]}, {"name": "NTHU_Taiwan", "children": [{"name": "Education / outreach event", "children": [{"name": 1287, "value": 8}]}, {"name": "Meetups", "children": [{"name": 1287, "value": 2}]}, {"name": "No iGEM work", "children": [{"name": 1287, "value": 7}]}, {"name": "Planning tasks", "children": [{"name": 1287, "value": 5}]}, {"name": "Team meetings", "children": [{"name": 1287, "value": 3}]}, {"name": "Writing / preparing presentations", "children": [{"name": 1287, "value": 1}]}]}, {"name": "Nantes", "children": [{"name": "Brainstorming", "children": [{"name": 1122, "value": 1}, {"name": 1134, "value": 1}, {"name": 2359, "value": 2}, {"name": 2361, "value": 4}]}, {"name": "Meetups", "children": [{"name": 2359, "value": 1}, {"name": 2361, "value": 4}]}, {"name": "Planning tasks", "children": [{"name": 1134, "value": 1}, {"name": 2361, "value": 6}]}, {"name": "Project administration", "children": [{"name": 2359, "value": 1}]}, {"name": "Reading papers or other material", "children": [{"name": 1134, "value": 1}]}, {"name": "Team meetings", "children": [{"name": 1117, "value": 2}, {"name": 1129, "value": 3}, {"name": 2359, "value": 11}, {"name": 2361, "value": 14}]}, {"name": "Writing / preparing presentations", "children": [{"name": 2361, "value": 4}]}]}, {"name": "OhioState", "children": [{"name": "Brainstorming", "children": [{"name": 1343, "value": 1}, {"name": 2368, "value": 1}]}, {"name": "Planning tasks", "children": [{"name": 2368, "value": 2}]}, {"name": "Reading papers or other material", "children": [{"name": 2368, "value": 1}]}, {"name": "Software development", "children": [{"name": 1343, "value": 1}]}, {"name": "Team meetings", "children": [{"name": 1343, "value": 1}]}, {"name": "Writing / preparing presentations", "children": [{"name": 1343, "value": 1}]}]}, {"name": "RUM-UPRM", "children": [{"name": "Analysing results", "children": [{"name": 2394, "value": 1}]}, {"name": "Brainstorming", "children": [{"name": 2391, "value": 1}, {"name": 2393, "value": 1}, {"name": 2394, "value": 4}, {"name": 2395, "value": 1}, {"name": 2396, "value": 1}, {"name": 2397, "value": 2}, {"name": 2405, "value": 3}, {"name": 2406, "value": 2}, {"name": 2407, "value": 2}, {"name": 2408, "value": 2}, {"name": 2409, "value": 2}, {"name": 2410, "value": 3}]}, {"name": "Collecting data / running assays", "children": [{"name": 2394, "value": 1}]}, {"name": "Developing protocols", "children": [{"name": 2396, "value": 1}, {"name": 2410, "value": 1}]}, {"name": "Education / outreach event", "children": [{"name": 2394, "value": 6}, {"name": 2396, "value": 1}, {"name": 2397, "value": 7}, {"name": 2399, "value": 7}, {"name": 2405, "value": 5}, {"name": 2407, "value": 2}, {"name": 2408, "value": 2}, {"name": 2410, "value": 5}]}, {"name": "Education event", "children": [{"name": 2394, "value": 6}, {"name": 2396, "value": 1}, {"name": 2397, "value": 7}, {"name": 2399, "value": 7}, {"name": 2405, "value": 7}, {"name": 2410, "value": 2}]}, {"name": "Hardware development", "children": [{"name": 2394, "value": 1}, {"name": 2407, "value": 2}]}, {"name": "Lab maintenance", "children": [{"name": 2394, "value": 1}]}, {"name": "Meetups", "children": [{"name": 2382, "value": 1}, {"name": 2393, "value": 1}, {"name": 2394, "value": 8}, {"name": 2397, "value": 20}, {"name": 2399, "value": 4}, {"name": 2406, "value": 1}, {"name": 2409, "value": 7}]}, {"name": "No iGEM work", "children": [{"name": 2397, "value": 2}, {"name": 2405, "value": 1}]}, {"name": "Planning tasks", "children": [{"name": 2391, "value": 1}, {"name": 2393, "value": 1}, {"name": 2394, "value": 8}, {"name": 2397, "value": 5}, {"name": 2405, "value": 3}, {"name": 2406, "value": 2}, {"name": 2407, "value": 2}, {"name": 2408, "value": 2}, {"name": 2409, "value": 7}, {"name": 2410, "value": 2}]}, {"name": "Preparing samples", "children": [{"name": 2394, "value": 1}]}, {"name": "Project administration", "children": [{"name": 2397, "value": 3}, {"name": 2405, "value": 2}]}, {"name": "Reading papers or other material", "children": [{"name": 2391, "value": 3}, {"name": 2394, "value": 1}, {"name": 2395, "value": 1}, {"name": 2406, "value": 1}]}, {"name": "Software development", "children": [{"name": 2394, "value": 1}]}, {"name": "Team meetings", "children": [{"name": 2391, "value": 5}, {"name": 2394, "value": 6}, {"name": 2396, "value": 1}, {"name": 2397, "value": 20}, {"name": 2398, "value": 1}, {"name": 2401, "value": 4}, {"name": 2404, "value": 2}, {"name": 2405, "value": 6}, {"name": 2406, "value": 3}, {"name": 2407, "value": 2}, {"name": 2408, "value": 2}, {"name": 2409, "value": 6}, {"name": 2410, "value": 9}]}, {"name": "Writing / preparing presentations", "children": [{"name": 2391, "value": 3}, {"name": 2395, "value": 1}, {"name": 2397, "value": 4}, {"name": 2408, "value": 1}]}]}]}
